README.md
setup.cfg
setup.py
HBdataMonitor/HBdataMonitor.py
HBdataMonitor/__init__.py
HBdataMonitor.egg-info/PKG-INFO
HBdataMonitor.egg-info/SOURCES.txt
HBdataMonitor.egg-info/dependency_links.txt
HBdataMonitor.egg-info/not-zip-safe
HBdataMonitor.egg-info/top_level.txt