Metadata-Version: 2.1
Name: HBdataMonitor
Version: 1.0.0
Summary: Tool to visualize HB SQLite databases
Home-page: https://github.com/menno94/HBdataMonitor
Author: Menno de ridder
Author-email: menno.deridder@deltares.nl
License: MIT
Platform: UNKNOWN
Requires-Python: >=3, <4
